{"rating": 7.33, "links": [], "ratings_num": 3, "maingenre": "", "imdb": "tt0177507", "year": "1999", "plot": [""], "genres": ["", "", ""], "compose": [], "title": "Absolute Giganten", "plot_es": [""], "original_name": "Absolute Giganten", "mediaType": 2, "write": [], "plot_en": [""], "status": 3, "languages": [], "timestamp": 1419289200, "broadcast": "online", "produce": [], "total_users": 10, "id_media": "9ZR7AA6YWFHF3AV", "director": [], "rate_summary": {"aggregate": {"1": 0, "3": 1, "2": 0, "5": 0, "4": 2}}, "country": [], "cast": [], "idm": 596278, "episodeUserCreator": [], "aka": null, "runtime": "80"}