{"rating": 8.8, "ratings_num": 90, "maingenre": "Drama", "episodes": {"1": [{"num": 1, "name": "orgullo del 3er mundo, programa 01", "links": [{"lang": "Castellano", "info": "", "linksType": "streaming", "added": "2013-11-05 03:17:52", "sprite": "videomegatv", "idv": 3788993, "NickAddedBy": "Borju65", "price": "", "addedBy": 2400484, "url": "http://videomega.tv/?ref=SgVGZBKIEA", "host": "VideoMega.tv", "DateAdded": "2013-11-05", "features": "", "quality": "Alta", "UploadedBy": "Borju65", "sub": ""}, {"lang": "Castellano", "info": "", "linksType": "streaming", "added": "2013-03-17 23:25:57", "sprite": "youtube", "idv": 2094406, "NickAddedBy": "ertigre", "price": "", "addedBy": 2320036, "url": "http://youtube.com/watch?v=7pbe417hwJs", "host": "Youtube", "DateAdded": "2013-03-17", "features": "", "quality": "Baja", "UploadedBy": "ertigre", "sub": ""}, {"lang": "Castellano", "info": "", "linksType": "direct_download", "added": "2014-11-30 16:58:27", "sprite": "freakshare", "idv": 11294462, "NickAddedBy": "parak314", "price": "", "addedBy": 3319309, "url": "http://freakshare.com/files/d8fresly/Fmn.y.Cnsd.El.Orgll.dl.Trcr.Mnd.01.ByParak.avi.html", "host": "FreakShare", "DateAdded": "2014-11-30", "features": "", "quality": "Alta", "UploadedBy": "parak314", "sub": ""}, {"lang": "Castellano", "info": "", "linksType": "direct_download", "added": "2014-11-30 16:55:19", "sprite": "bitshare", "idv": 11294437, "NickAddedBy": "parak314", "price": "", "addedBy": 3319309, "url": "http://bitshare.com/?f=9avm24o0", "host": "BitShare", "DateAdded": "2014-11-30", "features": "", "quality": "Alta", "UploadedBy": "parak314", "sub": ""}, {"lang": "Castellano", "info": "", "linksType": "direct_download", "added": "2014-11-30 16:53:29", "sprite": "uploaded", "idv": 11294419, "NickAddedBy": "parak314", "price": "", "addedBy": 3319309, "url": "http://uploaded.to/file/u7mti5vl", "host": "uploaded", "DateAdded": "2014-11-30", "features": "", "quality": "Alta", "UploadedBy": "parak314", "sub": ""}, {"lang": "Castellano", "info": "", "linksType": "direct_download", "added": "2014-04-22 14:31:48", "sprite": "uploaded", "idv": 6164476, "NickAddedBy": "jorgereal", "price": "", "addedBy": 3581305, "url": "http://uploaded.to/file/xc2rdfo4", "host": "uploaded", "DateAdded": "2014-04-22", "features": "", "quality": "Alta", "UploadedBy": "jorgereal", "sub": ""}, {"lang": "Castellano", "info": "", "linksType": "direct_download", "added": "2013-12-09 23:34:37", "sprite": "letitbit", "idv": 4213891, "NickAddedBy": "conturera", "price": "", "addedBy": 3136890, "url": "http://letitbit.net/download/89938.80768671540c6147a0cc0b8899ee/Faemino_y_Cansado_-_El_Orgullo_del_Tercer_Mundo_Capitulo_1x01.avi.html", "host": "Letitbit", "DateAdded": "2013-12-09", "features": "", "quality": "Alta", "UploadedBy": "conturera", "sub": ""}, {"lang": "Castellano", "info": "", "linksType": "direct_download", "added": "2013-10-18 10:57:16", "sprite": "bitshare", "idv": 3628819, "NickAddedBy": "Borju65", "price": "", "addedBy": 2400484, "url": "http://bitshare.com/?f=znafd0gn", "host": "BitShare", "DateAdded": "2013-10-18", "features": "", "quality": "Alta", "UploadedBy": "Borju65", "sub": ""}], "title": "orgullo del 3er mundo, programa 01", "season": 1, "mediaType": "1", "ids": 3799, "title_es": "orgullo del 3er mundo, programa 01", "has_links": true, "haveLinks": true, "timestamp": 1417363107, "episode": 1, "idc": 488380}, {"num": 2, "name": "orgullo del 3er mundo , programa 02", "links": [{"lang": "Castellano", "info": "", "linksType": "streaming", "added": "2013-11-26 11:27:12", "sprite": "playedto", "idv": 3995746, "NickAddedBy": "Borju65", "price": "", "addedBy": 2400484, "url": "http://played.to/w4iwf9wbt1bn", "host": "Played.to", "DateAdded": "2013-11-26", "features": "", "quality": "Alta", "UploadedBy": "Borju65", "sub": ""}, {"lang": "Castellano", "info": "", "linksType": "streaming", "added": "2013-11-05 03:17:52", "sprite": "videomegatv", "idv": 3788994, "NickAddedBy": "Borju65", "price": "", "addedBy": 2400484, "url": "http://videomega.tv/?ref=STdcJOFOIV", "host": "VideoMega.tv", "DateAdded": "2013-11-05", "features": "", "quality": "Alta", "UploadedBy": "Borju65", "sub": ""}, {"lang": "Castellano", "info": "", "linksType": "streaming", "added": "2013-03-17 23:27:49", "sprite": "youtube", "idv": 2094408, "NickAddedBy": "ertigre", "price": "", "addedBy": 2320036, "url": "http://youtube.com/watch?v=Wmhy7WvpImU", "host": "Youtube", "DateAdded": "2013-03-17", "features": "", "quality": "Baja", "UploadedBy": "ertigre", "sub": ""}, {"lang": "Castellano", "info": "", "linksType": "streaming", "added": "2013-11-05 03:17:52", "sprite": "videomegatv", "idv": 3788995, "NickAddedBy": "Borju65", "price": "", "addedBy": 2400484, "url": "http://videomega.tv/?ref=PIUfYceIGW", "host": "VideoMega.tv", "DateAdded": "2013-11-05", "features": "", "quality": "Alta", "UploadedBy": "Borju65", "sub": ""}, {"lang": "Castellano", "info": "", "linksType": "direct_download", "added": "2014-11-30 16:58:29", "sprite": "freakshare", "idv": 11294464, "NickAddedBy": "parak314", "price": "", "addedBy": 3319309, "url": "http://freakshare.com/files/saqqx2mt/Fmn.y.Cnsd.El.Orgll.dl.Trcr.Mnd.02.ByParak.avi.html", "host": "FreakShare", "DateAdded": "2014-11-30", "features": "", "quality": "Alta", "UploadedBy": "parak314", "sub": ""}, {"lang": "Castellano", "info": "", "linksType": "direct_download", "added": "2014-11-30 16:55:22", "sprite": "bitshare", "idv": 11294438, "NickAddedBy": "parak314", "price": "", "addedBy": 3319309, "url": "http://bitshare.com/?f=5cow7dba", "host": "BitShare", "DateAdded": "2014-11-30", "features": "", "quality": "Alta", "UploadedBy": "parak314", "sub": ""}, {"lang": "Castellano", "info": "", "linksType": "direct_download", "added": "2014-11-30 16:53:31", "sprite": "uploaded", "idv": 11294420, "NickAddedBy": "parak314", "price": "", "addedBy": 3319309, "url": "http://uploaded.to/file/zex8i9b8", "host": "uploaded", "DateAdded": "2014-11-30", "features": "", "quality": "Alta", "UploadedBy": "parak314", "sub": ""}, {"lang": "Castellano", "info": "", "linksType": "direct_download", "added": "2014-04-22 14:31:49", "sprite": "uploaded", "idv": 6164477, "NickAddedBy": "jorgereal", "price": "", "addedBy": 3581305, "url": "http://uploaded.to/file/g0s3sdmt", "host": "uploaded", "DateAdded": "2014-04-22", "features": "", "quality": "Alta", "UploadedBy": "jorgereal", "sub": ""}, {"lang": "Castellano", "info": "", "linksType": "direct_download", "added": "2013-12-09 23:34:39", "sprite": "letitbit", "idv": 4213893, "NickAddedBy": "conturera", "price": "", "addedBy": 3136890, "url": "http://letitbit.net/download/65202.63c542ee22a8a70325e79dcc50e1/Faemino_y_Cansado_-_El_Orgullo_del_Tercer_Mundo_Capitulo_1x02.avi.html", "host": "Letitbit", "DateAdded": "2013-12-09", "features": "", "quality": "Alta", "UploadedBy": "conturera", "sub": ""}, {"lang": "Castellano", "info": "", "linksType": "direct_download", "added": "2013-10-18 10:57:19", "sprite": "bitshare", "idv": 3628821, "NickAddedBy": "Borju65", "price": "", "addedBy": 2400484, "url": "http://bitshare.com/?f=t3ayfbk9", "host": "BitShare", "DateAdded": "2013-10-18", "features": "", "quality": "Alta", "UploadedBy": "Borju65", "sub": ""}, {"lang": "Castellano", "info": "", "linksType": "direct_download", "added": "2013-10-18 10:57:18", "sprite": "bitshare", "idv": 3628820, "NickAddedBy": "Borju65", "price": "", "addedBy": 2400484, "url": "http://bitshare.com/?f=matz5vfn", "host": "BitShare", "DateAdded": "2013-10-18", "features": "", "quality": "Alta", "UploadedBy": "Borju65", "sub": ""}], "title": "orgullo del 3er mundo , programa 02", "season": 1, "mediaType": "1", "ids": 3799, "title_es": "orgullo del 3er mundo , programa 02", "has_links": true, "haveLinks": true, "timestamp": 1417363109, "episode": 2, "idc": 488381}, {"num": 3, "name": "Orgullo del 3er mundo , programa 03", "links": [{"lang": "Castellano", "info": "", "linksType": "streaming", "added": "2013-11-26 11:27:13", "sprite": "playedto", "idv": 3995747, "NickAddedBy": "Borju65", "price": "", "addedBy": 2400484, "url": "http://played.to/afdn10rn2d44", "host": "Played.to", "DateAdded": "2013-11-26", "features": "", "quality": "Alta", "UploadedBy": "Borju65", "sub": ""}, {"lang": "Castellano", "info": "", "linksType": "direct_download", "added": "2014-11-30 16:58:30", "sprite": "freakshare", "idv": 11294465, "NickAddedBy": "parak314", "price": "", "addedBy": 3319309, "url": "http://freakshare.com/files/auzjeq0l/Fmn.y.Cnsd.El.Orgll.dl.Trcr.Mnd.03.ByParak.avi.html", "host": "FreakShare", "DateAdded": "2014-11-30", "features": "", "quality": "Alta", "UploadedBy": "parak314", "sub": ""}, {"lang": "Castellano", "info": "", "linksType": "direct_download", "added": "2014-11-30 16:55:25", "sprite": "bitshare", "idv": 11294439, "NickAddedBy": "parak314", "price": "", "addedBy": 3319309, "url": "http://bitshare.com/?f=d2ybr2ld", "host": "BitShare", "DateAdded": "2014-11-30", "features": "", "quality": "Alta", "UploadedBy": "parak314", "sub": ""}, {"lang": "Castellano", "info": "", "linksType": "direct_download", "added": "2014-11-30 16:53:33", "sprite": "uploaded", "idv": 11294421, "NickAddedBy": "parak314", "price": "", "addedBy": 3319309, "url": "http://uploaded.to/file/8a7t6wy9", "host": "uploaded", "DateAdded": "2014-11-30", "features": "", "quality": "Alta", "UploadedBy": "parak314", "sub": ""}, {"lang": "Castellano", "info": "", "linksType": "direct_download", "added": "2014-04-22 14:31:51", "sprite": "uploaded", "idv": 6164478, "NickAddedBy": "jorgereal", "price": "", "addedBy": 3581305, "url": "http://uploaded.to/file/enqsjtl5", "host": "uploaded", "DateAdded": "2014-04-22", "features": "", "quality": "Alta", "UploadedBy": "jorgereal", "sub": ""}, {"lang": "Castellano", "info": "", "linksType": "direct_download", "added": "2013-12-09 23:34:41", "sprite": "letitbit", "idv": 4213895, "NickAddedBy": "conturera", "price": "", "addedBy": 3136890, "url": "http://letitbit.net/download/53988.5cf5dd68e0554cfa414b6bf372b8/Faemino_y_Cansado_-_El_Orgullo_del_Tercer_Mundo_Capitulo_1x03.avi.html", "host": "Letitbit", "DateAdded": "2013-12-09", "features": "", "quality": "Alta", "UploadedBy": "conturera", "sub": ""}], "title": "Orgullo del 3er mundo , programa 03", "season": 1, "mediaType": "1", "ids": 3799, "title_es": "Orgullo del 3er mundo , programa 03", "has_links": true, "haveLinks": true, "timestamp": 1417363110, "episode": 3, "idc": 591779}, {"num": 4, "name": "Capitulo 04", "links": [{"lang": "Castellano", "info": "", "linksType": "streaming", "added": "2013-01-13 23:44:57", "sprite": "youtube", "idv": 1714868, "NickAddedBy": "egidous", "price": "", "addedBy": 1183273, "url": "http://youtube.com/watch?v=DM2sHlP27YE", "host": "Youtube", "DateAdded": "2013-01-13", "features": "", "quality": "Alta", "UploadedBy": "egidous", "sub": ""}, {"lang": "Castellano", "info": "", "linksType": "streaming", "added": "2013-11-05 03:17:52", "sprite": "videomegatv", "idv": 3788996, "NickAddedBy": "Borju65", "price": "", "addedBy": 2400484, "url": "http://videomega.tv/?ref=bgLHUNXDbb", "host": "VideoMega.tv", "DateAdded": "2013-11-05", "features": "", "quality": "Alta", "UploadedBy": "Borju65", "sub": ""}, {"lang": "Castellano", "info": "", "linksType": "streaming", "added": "2013-11-26 11:27:15", "sprite": "playedto", "idv": 3995748, "NickAddedBy": "Borju65", "price": "", "addedBy": 2400484, "url": "http://played.to/txy4ad75vqjf", "host": "Played.to", "DateAdded": "2013-11-26", "features": "", "quality": "Alta", "UploadedBy": "Borju65", "sub": ""}, {"lang": "Castellano", "info": "", "linksType": "direct_download", "added": "2014-11-30 16:58:32", "sprite": "freakshare", "idv": 11294466, "NickAddedBy": "parak314", "price": "", "addedBy": 3319309, "url": "http://freakshare.com/files/n8lrlsc0/Fmn.y.Cnsd.El.Orgll.dl.Trcr.Mnd.04.ByParak.avi.html", "host": "FreakShare", "DateAdded": "2014-11-30", "features": "", "quality": "Alta", "UploadedBy": "parak314", "sub": ""}, {"lang": "Castellano", "info": "", "linksType": "direct_download", "added": "2014-11-30 16:55:28", "sprite": "bitshare", "idv": 11294440, "NickAddedBy": "parak314", "price": "", "addedBy": 3319309, "url": "http://bitshare.com/?f=389t0icb", "host": "BitShare", "DateAdded": "2014-11-30", "features": "", "quality": "Alta", "UploadedBy": "parak314", "sub": ""}, {"lang": "Castellano", "info": "", "linksType": "direct_download", "added": "2014-11-30 16:53:35", "sprite": "uploaded", "idv": 11294422, "NickAddedBy": "parak314", "price": "", "addedBy": 3319309, "url": "http://uploaded.to/file/m5e23aeo", "host": "uploaded", "DateAdded": "2014-11-30", "features": "", "quality": "Alta", "UploadedBy": "parak314", "sub": ""}, {"lang": "Castellano", "info": "", "linksType": "direct_download", "added": "2014-04-22 14:31:53", "sprite": "uploaded", "idv": 6164479, "NickAddedBy": "jorgereal", "price": "", "addedBy": 3581305, "url": "http://uploaded.to/file/yum2a70m", "host": "uploaded", "DateAdded": "2014-04-22", "features": "", "quality": "Alta", "UploadedBy": "jorgereal", "sub": ""}, {"lang": "Castellano", "info": "", "linksType": "direct_download", "added": "2013-12-09 23:34:42", "sprite": "letitbit", "idv": 4213896, "NickAddedBy": "conturera", "price": "", "addedBy": 3136890, "url": "http://letitbit.net/download/87815.86a70fd941b9494abad450fbaa00/Faemino_y_Cansado_-_El_Orgullo_del_Tercer_Mundo_Capitulo_1x04.avi.html", "host": "Letitbit", "DateAdded": "2013-12-09", "features": "", "quality": "Alta", "UploadedBy": "conturera", "sub": ""}, {"lang": "Castellano", "info": "", "linksType": "direct_download", "added": "2013-10-18 10:57:20", "sprite": "bitshare", "idv": 3628822, "NickAddedBy": "Borju65", "price": "", "addedBy": 2400484, "url": "http://bitshare.com/?f=u7lpohse", "host": "BitShare", "DateAdded": "2013-10-18", "features": "", "quality": "Alta", "UploadedBy": "Borju65", "sub": ""}], "title": "Capitulo 04", "season": 1, "mediaType": "1", "ids": 3799, "title_es": "Capitulo 04", "has_links": true, "haveLinks": true, "timestamp": 1417363112, "episode": 4, "idc": 90539}, {"num": 5, "name": "Capitulo 05", "links": [{"lang": "Castellano", "info": "", "linksType": "streaming", "added": "2013-11-05 03:17:53", "sprite": "videomegatv", "idv": 3788997, "NickAddedBy": "Borju65", "price": "", "addedBy": 2400484, "url": "http://videomega.tv/?ref=dfFOFLaGfD", "host": "VideoMega.tv", "DateAdded": "2013-11-05", "features": "", "quality": "Alta", "UploadedBy": "Borju65", "sub": ""}, {"lang": "Castellano", "info": "", "linksType": "streaming", "added": "2013-05-24 01:29:36", "sprite": "youtube", "idv": 2456038, "NickAddedBy": "Desamparado", "price": "", "addedBy": 50059, "url": "http://youtube.com/watch?v=fVgBAiO7bWc", "host": "Youtube", "DateAdded": "2013-05-24", "features": "", "quality": "Alta", "UploadedBy": "Desamparado", "sub": ""}, {"lang": "Castellano", "info": "", "linksType": "streaming", "added": "2013-11-26 11:27:16", "sprite": "playedto", "idv": 3995749, "NickAddedBy": "Borju65", "price": "", "addedBy": 2400484, "url": "http://played.to/eddrr8gsi49r", "host": "Played.to", "DateAdded": "2013-11-26", "features": "", "quality": "Alta", "UploadedBy": "Borju65", "sub": ""}, {"lang": "Castellano", "info": "", "linksType": "direct_download", "added": "2014-11-30 16:58:33", "sprite": "freakshare", "idv": 11294467, "NickAddedBy": "parak314", "price": "", "addedBy": 3319309, "url": "http://freakshare.com/files/ncjacx1z/Fmn.y.Cnsd.El.Orgll.dl.Trcr.Mnd.05.ByParak.avi.html", "host": "FreakShare", "DateAdded": "2014-11-30", "features": "", "quality": "Alta", "UploadedBy": "parak314", "sub": ""}, {"lang": "Castellano", "info": "", "linksType": "direct_download", "added": "2014-11-30 16:55:32", "sprite": "bitshare", "idv": 11294441, "NickAddedBy": "parak314", "price": "", "addedBy": 3319309, "url": "http://bitshare.com/?f=sw1ohqhd", "host": "BitShare", "DateAdded": "2014-11-30", "features": "", "quality": "Alta", "UploadedBy": "parak314", "sub": ""}, {"lang": "Castellano", "info": "", "linksType": "direct_download", "added": "2014-11-30 16:53:36", "sprite": "uploaded", "idv": 11294423, "NickAddedBy": "parak314", "price": "", "addedBy": 3319309, "url": "http://uploaded.to/file/0pmsex7t", "host": "uploaded", "DateAdded": "2014-11-30", "features": "", "quality": "Alta", "UploadedBy": "parak314", "sub": ""}, {"lang": "Castellano", "info": "", "linksType": "direct_download", "added": "2014-04-22 14:31:54", "sprite": "uploaded", "idv": 6164480, "NickAddedBy": "jorgereal", "price": "", "addedBy": 3581305, "url": "http://uploaded.to/file/ief8m4sn", "host": "uploaded", "DateAdded": "2014-04-22", "features": "", "quality": "Alta", "UploadedBy": "jorgereal", "sub": ""}, {"lang": "Castellano", "info": "", "linksType": "direct_download", "added": "2013-12-09 23:34:47", "sprite": "letitbit", "idv": 4213899, "NickAddedBy": "conturera", "price": "", "addedBy": 3136890, "url": "http://letitbit.net/download/17209.100c9f982f2e3fda3cb821cc02fe/Faemino_y_Cansado_-_El_Orgullo_del_Tercer_Mundo_Capitulo_1x05.avi.html", "host": "Letitbit", "DateAdded": "2013-12-09", "features": "", "quality": "Alta", "UploadedBy": "conturera", "sub": ""}, {"lang": "Castellano", "info": "", "linksType": "direct_download", "added": "2013-10-18 10:57:21", "sprite": "bitshare", "idv": 3628823, "NickAddedBy": "Borju65", "price": "", "addedBy": 2400484, "url": "http://bitshare.com/?f=5gf9xsx1", "host": "BitShare", "DateAdded": "2013-10-18", "features": "", "quality": "Alta", "UploadedBy": "Borju65", "sub": ""}], "title": "Capitulo 05", "season": 1, "mediaType": "1", "ids": 3799, "title_es": "Capitulo 05", "has_links": true, "haveLinks": true, "timestamp": 1417363113, "episode": 5, "idc": 90540}, {"num": 6, "name": "Capitulo 06", "links": [{"lang": "Castellano", "info": "", "linksType": "streaming", "added": "2013-11-05 03:17:53", "sprite": "videomegatv", "idv": 3788998, "NickAddedBy": "Borju65", "price": "", "addedBy": 2400484, "url": "http://videomega.tv/?ref=dYPQIEKcJW", "host": "VideoMega.tv", "DateAdded": "2013-11-05", "features": "", "quality": "Alta", "UploadedBy": "Borju65", "sub": ""}, {"lang": "Castellano", "info": "", "linksType": "streaming", "added": "2013-05-24 01:30:13", "sprite": "youtube", "idv": 2456042, "NickAddedBy": "Desamparado", "price": "", "addedBy": 50059, "url": "http://youtube.com/watch?v=IrRLyDxc3DE", "host": "Youtube", "DateAdded": "2013-05-24", "features": "", "quality": "Baja", "UploadedBy": "Desamparado", "sub": ""}, {"lang": "Castellano", "info": "", "linksType": "streaming", "added": "2013-11-26 11:27:17", "sprite": "playedto", "idv": 3995750, "NickAddedBy": "Borju65", "price": "", "addedBy": 2400484, "url": "http://played.to/35bcekbsh1cm", "host": "Played.to", "DateAdded": "2013-11-26", "features": "", "quality": "Alta", "UploadedBy": "Borju65", "sub": ""}, {"lang": "Castellano", "info": "", "linksType": "direct_download", "added": "2014-11-30 16:58:35", "sprite": "freakshare", "idv": 11294468, "NickAddedBy": "parak314", "price": "", "addedBy": 3319309, "url": "http://freakshare.com/files/f9afw99c/Fmn.y.Cnsd.El.Orgll.dl.Trcr.Mnd.06.ByParak.avi.html", "host": "FreakShare", "DateAdded": "2014-11-30", "features": "", "quality": "Alta", "UploadedBy": "parak314", "sub": ""}, {"lang": "Castellano", "info": "", "linksType": "direct_download", "added": "2014-11-30 16:55:35", "sprite": "bitshare", "idv": 11294442, "NickAddedBy": "parak314", "price": "", "addedBy": 3319309, "url": "http://bitshare.com/?f=isan58yg", "host": "BitShare", "DateAdded": "2014-11-30", "features": "", "quality": "Alta", "UploadedBy": "parak314", "sub": ""}, {"lang": "Castellano", "info": "", "linksType": "direct_download", "added": "2014-11-30 16:53:38", "sprite": "uploaded", "idv": 11294424, "NickAddedBy": "parak314", "price": "", "addedBy": 3319309, "url": "http://uploaded.to/file/m68acxba", "host": "uploaded", "DateAdded": "2014-11-30", "features": "", "quality": "Alta", "UploadedBy": "parak314", "sub": ""}, {"lang": "Castellano", "info": "", "linksType": "direct_download", "added": "2014-04-22 14:31:56", "sprite": "uploaded", "idv": 6164481, "NickAddedBy": "jorgereal", "price": "", "addedBy": 3581305, "url": "http://uploaded.to/file/z4ydl2kb", "host": "uploaded", "DateAdded": "2014-04-22", "features": "", "quality": "Alta", "UploadedBy": "jorgereal", "sub": ""}, {"lang": "Castellano", "info": "", "linksType": "direct_download", "added": "2013-12-09 23:34:50", "sprite": "letitbit", "idv": 4213901, "NickAddedBy": "conturera", "price": "", "addedBy": 3136890, "url": "http://letitbit.net/download/77371.7bf0f52fa52ea0753dcb01f4e799/Faemino_y_Cansado_-_El_Orgullo_del_Tercer_Mundo_Capitulo_1x06.avi.html", "host": "Letitbit", "DateAdded": "2013-12-09", "features": "", "quality": "Alta", "UploadedBy": "conturera", "sub": ""}, {"lang": "Castellano", "info": "", "linksType": "direct_download", "added": "2013-10-18 10:57:22", "sprite": "bitshare", "idv": 3628824, "NickAddedBy": "Borju65", "price": "", "addedBy": 2400484, "url": "http://bitshare.com/?f=gl04os1n", "host": "BitShare", "DateAdded": "2013-10-18", "features": "", "quality": "Alta", "UploadedBy": "Borju65", "sub": ""}], "title": "Capitulo 06", "season": 1, "mediaType": "1", "ids": 3799, "title_es": "Capitulo 06", "has_links": true, "haveLinks": true, "timestamp": 1417363115, "episode": 6, "idc": 90541}, {"num": 7, "name": "Capitulo 07", "links": [{"lang": "Castellano", "info": "", "linksType": "streaming", "added": "2013-11-26 11:27:19", "sprite": "playedto", "idv": 3995751, "NickAddedBy": "Borju65", "price": "", "addedBy": 2400484, "url": "http://played.to/wwevfweh87dw", "host": "Played.to", "DateAdded": "2013-11-26", "features": "", "quality": "Alta", "UploadedBy": "Borju65", "sub": ""}, {"lang": "Castellano", "info": "", "linksType": "streaming", "added": "2013-11-05 03:17:53", "sprite": "videomegatv", "idv": 3788999, "NickAddedBy": "Borju65", "price": "", "addedBy": 2400484, "url": "http://videomega.tv/?ref=MMMNQWaPcI", "host": "VideoMega.tv", "DateAdded": "2013-11-05", "features": "", "quality": "Alta", "UploadedBy": "Borju65", "sub": ""}, {"lang": "Castellano", "info": "", "linksType": "streaming", "added": "2013-05-24 01:32:55", "sprite": "youtube", "idv": 2456044, "NickAddedBy": "Desamparado", "price": "", "addedBy": 50059, "url": "http://youtube.com/watch?v=1-6TQTw1Fes", "host": "Youtube", "DateAdded": "2013-05-24", "features": "", "quality": "Baja", "UploadedBy": "Desamparado", "sub": ""}, {"lang": "Castellano", "info": "", "linksType": "direct_download", "added": "2014-11-30 16:58:36", "sprite": "freakshare", "idv": 11294469, "NickAddedBy": "parak314", "price": "", "addedBy": 3319309, "url": "http://freakshare.com/files/bo5nlqww/Fmn.y.Cnsd.El.Orgll.dl.Trcr.Mnd.07.ByParak.avi.html", "host": "FreakShare", "DateAdded": "2014-11-30", "features": "", "quality": "Alta", "UploadedBy": "parak314", "sub": ""}, {"lang": "Castellano", "info": "", "linksType": "direct_download", "added": "2014-11-30 16:55:38", "sprite": "bitshare", "idv": 11294443, "NickAddedBy": "parak314", "price": "", "addedBy": 3319309, "url": "http://bitshare.com/?f=b8j4eqoe", "host": "BitShare", "DateAdded": "2014-11-30", "features": "", "quality": "Alta", "UploadedBy": "parak314", "sub": ""}, {"lang": "Castellano", "info": "", "linksType": "direct_download", "added": "2014-11-30 16:53:40", "sprite": "uploaded", "idv": 11294425, "NickAddedBy": "parak314", "price": "", "addedBy": 3319309, "url": "http://uploaded.to/file/wpysbrv9", "host": "uploaded", "DateAdded": "2014-11-30", "features": "", "quality": "Alta", "UploadedBy": "parak314", "sub": ""}, {"lang": "Castellano", "info": "", "linksType": "direct_download", "added": "2014-04-22 14:31:58", "sprite": "uploaded", "idv": 6164484, "NickAddedBy": "jorgereal", "price": "", "addedBy": 3581305, "url": "http://uploaded.to/file/u8boxhhx", "host": "uploaded", "DateAdded": "2014-04-22", "features": "", "quality": "Alta", "UploadedBy": "jorgereal", "sub": ""}, {"lang": "Castellano", "info": "", "linksType": "direct_download", "added": "2013-12-09 23:34:52", "sprite": "letitbit", "idv": 4213903, "NickAddedBy": "conturera", "price": "", "addedBy": 3136890, "url": "http://letitbit.net/download/47731.4e10e481e2f80bbab4c14b729c93/Faemino_y_Cansado_-_El_Orgullo_del_Tercer_Mundo_Capitulo_1x07.avi.html", "host": "Letitbit", "DateAdded": "2013-12-09", "features": "", "quality": "Alta", "UploadedBy": "conturera", "sub": ""}, {"lang": "Castellano", "info": "", "linksType": "direct_download", "added": "2013-10-18 10:57:23", "sprite": "bitshare", "idv": 3628825, "NickAddedBy": "Borju65", "price": "", "addedBy": 2400484, "url": "http://bitshare.com/?f=gncip239", "host": "BitShare", "DateAdded": "2013-10-18", "features": "", "quality": "Alta", "UploadedBy": "Borju65", "sub": ""}], "title": "Capitulo 07", "season": 1, "mediaType": "1", "ids": 3799, "title_es": "Capitulo 07", "has_links": true, "haveLinks": true, "timestamp": 1417363116, "episode": 7, "idc": 90542}, {"num": 8, "name": "Capitulo 08", "links": [{"lang": "Castellano", "info": "", "linksType": "streaming", "added": "2013-05-24 01:33:43", "sprite": "youtube", "idv": 2456046, "NickAddedBy": "Desamparado", "price": "", "addedBy": 50059, "url": "http://youtube.com/watch?v=BLsTFpssf2s", "host": "Youtube", "DateAdded": "2013-05-24", "features": "", "quality": "Baja", "UploadedBy": "Desamparado", "sub": ""}, {"lang": "Castellano", "info": "", "linksType": "streaming", "added": "2013-11-05 03:17:53", "sprite": "videomegatv", "idv": 3789000, "NickAddedBy": "Borju65", "price": "", "addedBy": 2400484, "url": "http://videomega.tv/?ref=IXVHQReQQJ", "host": "VideoMega.tv", "DateAdded": "2013-11-05", "features": "", "quality": "Alta", "UploadedBy": "Borju65", "sub": ""}, {"lang": "Castellano", "info": "", "linksType": "streaming", "added": "2013-11-26 11:27:21", "sprite": "playedto", "idv": 3995752, "NickAddedBy": "Borju65", "price": "", "addedBy": 2400484, "url": "http://played.to/j4cs2lo1iubj", "host": "Played.to", "DateAdded": "2013-11-26", "features": "", "quality": "Alta", "UploadedBy": "Borju65", "sub": ""}, {"lang": "Castellano", "info": "", "linksType": "direct_download", "added": "2014-11-30 16:58:38", "sprite": "freakshare", "idv": 11294471, "NickAddedBy": "parak314", "price": "", "addedBy": 3319309, "url": "http://freakshare.com/files/fqach8in/Fmn.y.Cnsd.El.Orgll.dl.Trcr.Mnd.08.ByParak.avi.html", "host": "FreakShare", "DateAdded": "2014-11-30", "features": "", "quality": "Alta", "UploadedBy": "parak314", "sub": ""}, {"lang": "Castellano", "info": "", "linksType": "direct_download", "added": "2014-11-30 16:55:41", "sprite": "bitshare", "idv": 11294444, "NickAddedBy": "parak314", "price": "", "addedBy": 3319309, "url": "http://bitshare.com/?f=1o9l8n6g", "host": "BitShare", "DateAdded": "2014-11-30", "features": "", "quality": "Alta", "UploadedBy": "parak314", "sub": ""}, {"lang": "Castellano", "info": "", "linksType": "direct_download", "added": "2014-11-30 16:53:41", "sprite": "uploaded", "idv": 11294426, "NickAddedBy": "parak314", "price": "", "addedBy": 3319309, "url": "http://uploaded.to/file/kyxfs3yw", "host": "uploaded", "DateAdded": "2014-11-30", "features": "", "quality": "Alta", "UploadedBy": "parak314", "sub": ""}, {"lang": "Castellano", "info": "", "linksType": "direct_download", "added": "2014-04-22 14:31:59", "sprite": "uploaded", "idv": 6164485, "NickAddedBy": "jorgereal", "price": "", "addedBy": 3581305, "url": "http://uploaded.to/file/odavhud2", "host": "uploaded", "DateAdded": "2014-04-22", "features": "", "quality": "Alta", "UploadedBy": "jorgereal", "sub": ""}, {"lang": "Castellano", "info": "", "linksType": "direct_download", "added": "2013-12-09 23:34:56", "sprite": "letitbit", "idv": 4213904, "NickAddedBy": "conturera", "price": "", "addedBy": 3136890, "url": "http://letitbit.net/download/87833.887524ce6f8556f9add1261e36cd/Faemino_y_Cansado_-_El_Orgullo_del_Tercer_Mundo_Capitulo_1x08.avi.html", "host": "Letitbit", "DateAdded": "2013-12-09", "features": "", "quality": "Alta", "UploadedBy": "conturera", "sub": ""}, {"lang": "Castellano", "info": "", "linksType": "direct_download", "added": "2013-10-18 10:57:25", "sprite": "bitshare", "idv": 3628826, "NickAddedBy": "Borju65", "price": "", "addedBy": 2400484, "url": "http://bitshare.com/?f=cs4b875j", "host": "BitShare", "DateAdded": "2013-10-18", "features": "", "quality": "Alta", "UploadedBy": "Borju65", "sub": ""}], "title": "Capitulo 08", "season": 1, "mediaType": "1", "ids": 3799, "title_es": "Capitulo 08", "has_links": true, "haveLinks": true, "timestamp": 1417363118, "episode": 8, "idc": 90543}, {"num": 9, "name": "Capitulo 09", "links": [{"lang": "Castellano", "info": "", "linksType": "streaming", "added": "2013-05-24 01:34:03", "sprite": "youtube", "idv": 2456047, "NickAddedBy": "Desamparado", "price": "", "addedBy": 50059, "url": "http://youtube.com/watch?v=VoHDkAU7kLQ", "host": "Youtube", "DateAdded": "2013-05-24", "features": "", "quality": "Baja", "UploadedBy": "Desamparado", "sub": ""}, {"lang": "Castellano", "info": "", "linksType": "streaming", "added": "2013-11-05 03:17:53", "sprite": "videomegatv", "idv": 3789001, "NickAddedBy": "Borju65", "price": "", "addedBy": 2400484, "url": "http://videomega.tv/?ref=gPGENHKdND", "host": "VideoMega.tv", "DateAdded": "2013-11-05", "features": "", "quality": "Alta", "UploadedBy": "Borju65", "sub": ""}, {"lang": "Castellano", "info": "", "linksType": "streaming", "added": "2013-11-26 11:27:23", "sprite": "playedto", "idv": 3995753, "NickAddedBy": "Borju65", "price": "", "addedBy": 2400484, "url": "http://played.to/nq00tax71ob1", "host": "Played.to", "DateAdded": "2013-11-26", "features": "", "quality": "Alta", "UploadedBy": "Borju65", "sub": ""}, {"lang": "Castellano", "info": "", "linksType": "direct_download", "added": "2014-11-30 16:58:39", "sprite": "freakshare", "idv": 11294472, "NickAddedBy": "parak314", "price": "", "addedBy": 3319309, "url": "http://freakshare.com/files/u01f8435/Fmn.y.Cnsd.El.Orgll.dl.Trcr.Mnd.09.ByParak.avi.html", "host": "FreakShare", "DateAdded": "2014-11-30", "features": "", "quality": "Alta", "UploadedBy": "parak314", "sub": ""}, {"lang": "Castellano", "info": "", "linksType": "direct_download", "added": "2014-11-30 16:57:52", "sprite": "bitshare", "idv": 11294452, "NickAddedBy": "parak314", "price": "", "addedBy": 3319309, "url": "http://bitshare.com/?f=5jgdg6le", "host": "BitShare", "DateAdded": "2014-11-30", "features": "", "quality": "Alta", "UploadedBy": "parak314", "sub": ""}, {"lang": "Castellano", "info": "", "linksType": "direct_download", "added": "2014-11-30 16:53:43", "sprite": "uploaded", "idv": 11294427, "NickAddedBy": "parak314", "price": "", "addedBy": 3319309, "url": "http://uploaded.to/file/p2e16cz1", "host": "uploaded", "DateAdded": "2014-11-30", "features": "", "quality": "Alta", "UploadedBy": "parak314", "sub": ""}, {"lang": "Castellano", "info": "", "linksType": "direct_download", "added": "2014-04-22 14:32:01", "sprite": "uploaded", "idv": 6164487, "NickAddedBy": "jorgereal", "price": "", "addedBy": 3581305, "url": "http://uploaded.to/file/9muickdb", "host": "uploaded", "DateAdded": "2014-04-22", "features": "", "quality": "Alta", "UploadedBy": "jorgereal", "sub": ""}, {"lang": "Castellano", "info": "", "linksType": "direct_download", "added": "2013-12-09 23:35:01", "sprite": "letitbit", "idv": 4213905, "NickAddedBy": "conturera", "price": "", "addedBy": 3136890, "url": "http://letitbit.net/download/80323.82b2831ebb7741e34d8e3a583ada/Faemino_y_Cansado_-_El_Orgullo_del_Tercer_Mundo_Capitulo_1x09.avi.html", "host": "Letitbit", "DateAdded": "2013-12-09", "features": "", "quality": "Alta", "UploadedBy": "conturera", "sub": ""}, {"lang": "Castellano", "info": "", "linksType": "direct_download", "added": "2013-10-18 10:57:26", "sprite": "bitshare", "idv": 3628827, "NickAddedBy": "Borju65", "price": "", "addedBy": 2400484, "url": "http://bitshare.com/?f=9vusaabr", "host": "BitShare", "DateAdded": "2013-10-18", "features": "", "quality": "Alta", "UploadedBy": "Borju65", "sub": ""}], "title": "Capitulo 09", "season": 1, "mediaType": "1", "ids": 3799, "title_es": "Capitulo 09", "has_links": true, "haveLinks": true, "timestamp": 1417363119, "episode": 9, "idc": 90544}, {"num": 10, "name": "Capitulo 10", "links": [{"lang": "Castellano", "info": "", "linksType": "streaming", "added": "2013-11-05 03:17:53", "sprite": "videomegatv", "idv": 3789002, "NickAddedBy": "Borju65", "price": "", "addedBy": 2400484, "url": "http://videomega.tv/?ref=cYVHUUfcST", "host": "VideoMega.tv", "DateAdded": "2013-11-05", "features": "", "quality": "Alta", "UploadedBy": "Borju65", "sub": ""}, {"lang": "Castellano", "info": "", "linksType": "streaming", "added": "2013-11-26 11:27:24", "sprite": "playedto", "idv": 3995754, "NickAddedBy": "Borju65", "price": "", "addedBy": 2400484, "url": "http://played.to/k8ggr2dn2tp7", "host": "Played.to", "DateAdded": "2013-11-26", "features": "", "quality": "Alta", "UploadedBy": "Borju65", "sub": ""}, {"lang": "Castellano", "info": "", "linksType": "streaming", "added": "2013-05-24 01:34:26", "sprite": "youtube", "idv": 2456050, "NickAddedBy": "Desamparado", "price": "", "addedBy": 50059, "url": "http://youtube.com/watch?v=TJDL0dLdTrE", "host": "Youtube", "DateAdded": "2013-05-24", "features": "", "quality": "Baja", "UploadedBy": "Desamparado", "sub": ""}, {"lang": "Castellano", "info": "", "linksType": "direct_download", "added": "2014-11-30 16:59:41", "sprite": "freakshare", "idv": 11294484, "NickAddedBy": "parak314", "price": "", "addedBy": 3319309, "url": "http://freakshare.com/files/23zu3by0/Fmn.y.Cnsd.El.Orgll.dl.Trcr.Mnd.10.ByParak.avi.html", "host": "FreakShare", "DateAdded": "2014-11-30", "features": "", "quality": "Alta", "UploadedBy": "parak314", "sub": ""}, {"lang": "Castellano", "info": "", "linksType": "direct_download", "added": "2014-11-30 16:57:55", "sprite": "bitshare", "idv": 11294453, "NickAddedBy": "parak314", "price": "", "addedBy": 3319309, "url": "http://bitshare.com/?f=ilhosdt2", "host": "BitShare", "DateAdded": "2014-11-30", "features": "", "quality": "Alta", "UploadedBy": "parak314", "sub": ""}, {"lang": "Castellano", "info": "", "linksType": "direct_download", "added": "2014-11-30 16:53:44", "sprite": "uploaded", "idv": 11294428, "NickAddedBy": "parak314", "price": "", "addedBy": 3319309, "url": "http://uploaded.to/file/t1yole8c", "host": "uploaded", "DateAdded": "2014-11-30", "features": "", "quality": "Alta", "UploadedBy": "parak314", "sub": ""}, {"lang": "Castellano", "info": "", "linksType": "direct_download", "added": "2014-04-22 14:32:02", "sprite": "uploaded", "idv": 6164489, "NickAddedBy": "jorgereal", "price": "", "addedBy": 3581305, "url": "http://uploaded.to/file/1s4sjsuu", "host": "uploaded", "DateAdded": "2014-04-22", "features": "", "quality": "Alta", "UploadedBy": "jorgereal", "sub": ""}, {"lang": "Castellano", "info": "", "linksType": "direct_download", "added": "2013-12-09 23:35:10", "sprite": "letitbit", "idv": 4213907, "NickAddedBy": "conturera", "price": "", "addedBy": 3136890, "url": "http://letitbit.net/download/22454.20555e08eba71efb1cc5e8511fa6/Faemino_y_Cansado_-_El_Orgullo_del_Tercer_Mundo_Capitulo_1x10.avi.html", "host": "Letitbit", "DateAdded": "2013-12-09", "features": "", "quality": "Alta", "UploadedBy": "conturera", "sub": ""}, {"lang": "Castellano", "info": "", "linksType": "direct_download", "added": "2013-10-18 10:57:27", "sprite": "bitshare", "idv": 3628828, "NickAddedBy": "Borju65", "price": "", "addedBy": 2400484, "url": "http://bitshare.com/?f=c42bgzvs", "host": "BitShare", "DateAdded": "2013-10-18", "features": "", "quality": "Alta", "UploadedBy": "Borju65", "sub": ""}], "title": "Capitulo 10", "season": 1, "mediaType": "1", "ids": 3799, "title_es": "Capitulo 10", "has_links": true, "haveLinks": true, "timestamp": 1417363181, "episode": 10, "idc": 90548}, {"num": 11, "name": "Capitulo 11", "links": [{"lang": "Castellano", "info": "", "linksType": "streaming", "added": "2013-11-26 11:27:25", "sprite": "playedto", "idv": 3995755, "NickAddedBy": "Borju65", "price": "", "addedBy": 2400484, "url": "http://played.to/395akun9xb84", "host": "Played.to", "DateAdded": "2013-11-26", "features": "", "quality": "Alta", "UploadedBy": "Borju65", "sub": ""}, {"lang": "Castellano", "info": "", "linksType": "streaming", "added": "2013-11-05 03:17:53", "sprite": "videomegatv", "idv": 3789003, "NickAddedBy": "Borju65", "price": "", "addedBy": 2400484, "url": "http://videomega.tv/?ref=XOAcdUeIZL", "host": "VideoMega.tv", "DateAdded": "2013-11-05", "features": "", "quality": "Alta", "UploadedBy": "Borju65", "sub": ""}, {"lang": "Castellano", "info": "", "linksType": "streaming", "added": "2013-05-24 01:34:43", "sprite": "youtube", "idv": 2456051, "NickAddedBy": "Desamparado", "price": "", "addedBy": 50059, "url": "http://youtube.com/watch?v=vOwFdyhMVZs", "host": "Youtube", "DateAdded": "2013-05-24", "features": "", "quality": "Baja", "UploadedBy": "Desamparado", "sub": ""}, {"lang": "Castellano", "info": "", "linksType": "direct_download", "added": "2014-11-30 16:59:32", "sprite": "freakshare", "idv": 11294477, "NickAddedBy": "parak314", "price": "", "addedBy": 3319309, "url": "http://freakshare.com/files/nw4ul398/Fmn.y.Cnsd.El.Orgll.dl.Trcr.Mnd.11.ByParak.avi.html", "host": "FreakShare", "DateAdded": "2014-11-30", "features": "", "quality": "Alta", "UploadedBy": "parak314", "sub": ""}, {"lang": "Castellano", "info": "", "linksType": "direct_download", "added": "2014-11-30 16:57:59", "sprite": "bitshare", "idv": 11294454, "NickAddedBy": "parak314", "price": "", "addedBy": 3319309, "url": "http://bitshare.com/?f=5gnhaz5r", "host": "BitShare", "DateAdded": "2014-11-30", "features": "", "quality": "Alta", "UploadedBy": "parak314", "sub": ""}, {"lang": "Castellano", "info": "", "linksType": "direct_download", "added": "2014-11-30 16:53:46", "sprite": "uploaded", "idv": 11294429, "NickAddedBy": "parak314", "price": "", "addedBy": 3319309, "url": "http://uploaded.to/file/8lzw5syc", "host": "uploaded", "DateAdded": "2014-11-30", "features": "", "quality": "Alta", "UploadedBy": "parak314", "sub": ""}, {"lang": "Castellano", "info": "", "linksType": "direct_download", "added": "2014-04-22 14:32:04", "sprite": "uploaded", "idv": 6164491, "NickAddedBy": "jorgereal", "price": "", "addedBy": 3581305, "url": "http://uploaded.to/file/alyph735", "host": "uploaded", "DateAdded": "2014-04-22", "features": "", "quality": "Alta", "UploadedBy": "jorgereal", "sub": ""}, {"lang": "Castellano", "info": "", "linksType": "direct_download", "added": "2013-12-09 23:35:16", "sprite": "letitbit", "idv": 4213910, "NickAddedBy": "conturera", "price": "", "addedBy": 3136890, "url": "http://letitbit.net/download/54752.51d48bdff1c8357a1f77ad2b67f5/Faemino_y_Cansado_-_El_Orgullo_del_Tercer_Mundo_Capitulo_1x11.avi.html", "host": "Letitbit", "DateAdded": "2013-12-09", "features": "", "quality": "Alta", "UploadedBy": "conturera", "sub": ""}, {"lang": "Castellano", "info": "", "linksType": "direct_download", "added": "2013-10-18 10:57:28", "sprite": "bitshare", "idv": 3628829, "NickAddedBy": "Borju65", "price": "", "addedBy": 2400484, "url": "http://bitshare.com/?f=4m4ie7uj", "host": "BitShare", "DateAdded": "2013-10-18", "features": "", "quality": "Alta", "UploadedBy": "Borju65", "sub": ""}], "title": "Capitulo 11", "season": 1, "mediaType": "1", "ids": 3799, "title_es": "Capitulo 11", "has_links": true, "haveLinks": true, "timestamp": 1417363172, "episode": 11, "idc": 90550}, {"num": 12, "name": "Capitulo 12", "links": [{"lang": "Castellano", "info": "", "linksType": "streaming", "added": "2013-11-05 03:17:54", "sprite": "videomegatv", "idv": 3789004, "NickAddedBy": "Borju65", "price": "", "addedBy": 2400484, "url": "http://videomega.tv/?ref=cHPFGQHMXG", "host": "VideoMega.tv", "DateAdded": "2013-11-05", "features": "", "quality": "Alta", "UploadedBy": "Borju65", "sub": ""}, {"lang": "Castellano", "info": "", "linksType": "streaming", "added": "2013-05-24 01:35:19", "sprite": "youtube", "idv": 2456052, "NickAddedBy": "Desamparado", "price": "", "addedBy": 50059, "url": "http://youtube.com/watch?v=pBnGPlasn6Q", "host": "Youtube", "DateAdded": "2013-05-24", "features": "", "quality": "Baja", "UploadedBy": "Desamparado", "sub": ""}, {"lang": "Castellano", "info": "", "linksType": "streaming", "added": "2013-11-26 11:27:26", "sprite": "playedto", "idv": 3995756, "NickAddedBy": "Borju65", "price": "", "addedBy": 2400484, "url": "http://played.to/pvt1q4jocka6", "host": "Played.to", "DateAdded": "2013-11-26", "features": "", "quality": "Alta", "UploadedBy": "Borju65", "sub": ""}, {"lang": "Castellano", "info": "", "linksType": "direct_download", "added": "2014-11-30 16:59:33", "sprite": "freakshare", "idv": 11294478, "NickAddedBy": "parak314", "price": "", "addedBy": 3319309, "url": "http://freakshare.com/files/5ccw83im/Fmn.y.Cnsd.El.Orgll.dl.Trcr.Mnd.12.ByParak.avi.html", "host": "FreakShare", "DateAdded": "2014-11-30", "features": "", "quality": "Alta", "UploadedBy": "parak314", "sub": ""}, {"lang": "Castellano", "info": "", "linksType": "direct_download", "added": "2014-11-30 16:58:02", "sprite": "bitshare", "idv": 11294456, "NickAddedBy": "parak314", "price": "", "addedBy": 3319309, "url": "http://bitshare.com/?f=b7exqjeb", "host": "BitShare", "DateAdded": "2014-11-30", "features": "", "quality": "Alta", "UploadedBy": "parak314", "sub": ""}, {"lang": "Castellano", "info": "", "linksType": "direct_download", "added": "2014-11-30 16:53:47", "sprite": "uploaded", "idv": 11294430, "NickAddedBy": "parak314", "price": "", "addedBy": 3319309, "url": "http://uploaded.to/file/1u1s1fyg", "host": "uploaded", "DateAdded": "2014-11-30", "features": "", "quality": "Alta", "UploadedBy": "parak314", "sub": ""}, {"lang": "Castellano", "info": "", "linksType": "direct_download", "added": "2014-04-22 14:32:06", "sprite": "uploaded", "idv": 6164494, "NickAddedBy": "jorgereal", "price": "", "addedBy": 3581305, "url": "http://uploaded.to/file/bku20ry6", "host": "uploaded", "DateAdded": "2014-04-22", "features": "", "quality": "Alta", "UploadedBy": "jorgereal", "sub": ""}, {"lang": "Castellano", "info": "", "linksType": "direct_download", "added": "2013-12-09 23:35:25", "sprite": "letitbit", "idv": 4213913, "NickAddedBy": "conturera", "price": "", "addedBy": 3136890, "url": "http://letitbit.net/download/92217.97b5186e7ec458d2b1723dc1f260/Faemino_y_Cansado_-_El_Orgullo_del_Tercer_Mundo_Capitulo_1x12.avi.html", "host": "Letitbit", "DateAdded": "2013-12-09", "features": "", "quality": "Alta", "UploadedBy": "conturera", "sub": ""}, {"lang": "Castellano", "info": "", "linksType": "direct_download", "added": "2013-10-18 10:57:30", "sprite": "bitshare", "idv": 3628830, "NickAddedBy": "Borju65", "price": "", "addedBy": 2400484, "url": "http://bitshare.com/?f=j9dz977c", "host": "BitShare", "DateAdded": "2013-10-18", "features": "", "quality": "Alta", "UploadedBy": "Borju65", "sub": ""}], "title": "Capitulo 12", "season": 1, "mediaType": "1", "ids": 3799, "title_es": "Capitulo 12", "has_links": true, "haveLinks": true, "timestamp": 1417363173, "episode": 12, "idc": 90552}, {"num": 13, "name": "Capitulo 13", "links": [{"lang": "Castellano", "info": "", "linksType": "streaming", "added": "2013-05-24 01:35:51", "sprite": "youtube", "idv": 2456053, "NickAddedBy": "Desamparado", "price": "", "addedBy": 50059, "url": "http://youtube.com/watch?v=uHXs3M7kdcw", "host": "Youtube", "DateAdded": "2013-05-24", "features": "", "quality": "Baja", "UploadedBy": "Desamparado", "sub": ""}, {"lang": "Castellano", "info": "", "linksType": "streaming", "added": "2013-11-26 11:27:28", "sprite": "playedto", "idv": 3995757, "NickAddedBy": "Borju65", "price": "", "addedBy": 2400484, "url": "http://played.to/4z5th6345gnm", "host": "Played.to", "DateAdded": "2013-11-26", "features": "", "quality": "Alta", "UploadedBy": "Borju65", "sub": ""}, {"lang": "Castellano", "info": "", "linksType": "streaming", "added": "2013-11-05 03:17:54", "sprite": "videomegatv", "idv": 3789005, "NickAddedBy": "Borju65", "price": "", "addedBy": 2400484, "url": "http://videomega.tv/?ref=fRgROVccEC", "host": "VideoMega.tv", "DateAdded": "2013-11-05", "features": "", "quality": "Alta", "UploadedBy": "Borju65", "sub": ""}, {"lang": "Castellano", "info": "", "linksType": "direct_download", "added": "2014-11-30 16:59:35", "sprite": "freakshare", "idv": 11294479, "NickAddedBy": "parak314", "price": "", "addedBy": 3319309, "url": "http://freakshare.com/files/gpukenfe/Fmn.y.Cnsd.El.Orgll.dl.Trcr.Mnd.13.ByParak.avi.html", "host": "FreakShare", "DateAdded": "2014-11-30", "features": "", "quality": "Alta", "UploadedBy": "parak314", "sub": ""}, {"lang": "Castellano", "info": "", "linksType": "direct_download", "added": "2014-11-30 16:58:05", "sprite": "bitshare", "idv": 11294457, "NickAddedBy": "parak314", "price": "", "addedBy": 3319309, "url": "http://bitshare.com/?f=ymidjn09", "host": "BitShare", "DateAdded": "2014-11-30", "features": "", "quality": "Alta", "UploadedBy": "parak314", "sub": ""}, {"lang": "Castellano", "info": "", "linksType": "direct_download", "added": "2014-11-30 16:53:49", "sprite": "uploaded", "idv": 11294431, "NickAddedBy": "parak314", "price": "", "addedBy": 3319309, "url": "http://uploaded.to/file/6qvniswh", "host": "uploaded", "DateAdded": "2014-11-30", "features": "", "quality": "Alta", "UploadedBy": "parak314", "sub": ""}, {"lang": "Castellano", "info": "", "linksType": "direct_download", "added": "2014-04-22 14:32:23", "sprite": "uploaded", "idv": 6164501, "NickAddedBy": "jorgereal", "price": "", "addedBy": 3581305, "url": "http://uploaded.to/file/a0lispw7", "host": "uploaded", "DateAdded": "2014-04-22", "features": "", "quality": "Alta", "UploadedBy": "jorgereal", "sub": ""}, {"lang": "Castellano", "info": "", "linksType": "direct_download", "added": "2013-12-09 23:35:27", "sprite": "letitbit", "idv": 4213915, "NickAddedBy": "conturera", "price": "", "addedBy": 3136890, "url": "http://letitbit.net/download/57751.505bad30c6d812bdcf79047fc01a/Faemino_y_Cansado_-_El_Orgullo_del_Tercer_Mundo_Capitulo_1x13.avi.html", "host": "Letitbit", "DateAdded": "2013-12-09", "features": "", "quality": "Alta", "UploadedBy": "conturera", "sub": ""}, {"lang": "Castellano", "info": "", "linksType": "direct_download", "added": "2013-10-18 10:57:31", "sprite": "bitshare", "idv": 3628831, "NickAddedBy": "Borju65", "price": "", "addedBy": 2400484, "url": "http://bitshare.com/?f=91emz5c2", "host": "BitShare", "DateAdded": "2013-10-18", "features": "", "quality": "Alta", "UploadedBy": "Borju65", "sub": ""}], "title": "Capitulo 13", "season": 1, "mediaType": "1", "ids": 3799, "title_es": "Capitulo 13", "has_links": true, "haveLinks": true, "timestamp": 1417363175, "episode": 13, "idc": 90554}, {"num": 14, "name": "Capitulo 14", "links": [{"lang": "Castellano", "info": "", "linksType": "streaming", "added": "2013-11-05 03:17:54", "sprite": "videomegatv", "idv": 3789006, "NickAddedBy": "Borju65", "price": "", "addedBy": 2400484, "url": "http://videomega.tv/?ref=TbTggWWPYV", "host": "VideoMega.tv", "DateAdded": "2013-11-05", "features": "", "quality": "Alta", "UploadedBy": "Borju65", "sub": ""}, {"lang": "Castellano", "info": "", "linksType": "streaming", "added": "2013-11-26 11:27:29", "sprite": "playedto", "idv": 3995758, "NickAddedBy": "Borju65", "price": "", "addedBy": 2400484, "url": "http://played.to/45gze40o6gkd", "host": "Played.to", "DateAdded": "2013-11-26", "features": "", "quality": "Alta", "UploadedBy": "Borju65", "sub": ""}, {"lang": "Castellano", "info": "", "linksType": "direct_download", "added": "2014-11-30 16:59:37", "sprite": "freakshare", "idv": 11294480, "NickAddedBy": "parak314", "price": "", "addedBy": 3319309, "url": "http://freakshare.com/files/fr4xuxme/Fmn.y.Cnsd.El.Orgll.dl.Trcr.Mnd.14.ByParak.avi.html", "host": "FreakShare", "DateAdded": "2014-11-30", "features": "", "quality": "Alta", "UploadedBy": "parak314", "sub": ""}, {"lang": "Castellano", "info": "", "linksType": "direct_download", "added": "2014-11-30 16:58:09", "sprite": "bitshare", "idv": 11294458, "NickAddedBy": "parak314", "price": "", "addedBy": 3319309, "url": "http://bitshare.com/?f=e7juqrte", "host": "BitShare", "DateAdded": "2014-11-30", "features": "", "quality": "Alta", "UploadedBy": "parak314", "sub": ""}, {"lang": "Castellano", "info": "", "linksType": "direct_download", "added": "2014-11-30 16:53:51", "sprite": "uploaded", "idv": 11294432, "NickAddedBy": "parak314", "price": "", "addedBy": 3319309, "url": "http://uploaded.to/file/21bzcbmb", "host": "uploaded", "DateAdded": "2014-11-30", "features": "", "quality": "Alta", "UploadedBy": "parak314", "sub": ""}, {"lang": "Castellano", "info": "", "linksType": "direct_download", "added": "2014-04-22 14:32:27", "sprite": "uploaded", "idv": 6164503, "NickAddedBy": "jorgereal", "price": "", "addedBy": 3581305, "url": "http://uploaded.to/file/xt9528pw", "host": "uploaded", "DateAdded": "2014-04-22", "features": "", "quality": "Alta", "UploadedBy": "jorgereal", "sub": ""}, {"lang": "Castellano", "info": "", "linksType": "direct_download", "added": "2013-12-09 23:35:29", "sprite": "letitbit", "idv": 4213916, "NickAddedBy": "conturera", "price": "", "addedBy": 3136890, "url": "http://letitbit.net/download/47074.4cd19ecd91cd4ffcad68f15ec18d/Faemino_y_Cansado_-_El_Orgullo_del_Tercer_Mundo_Capitulo_1x14.avi.html", "host": "Letitbit", "DateAdded": "2013-12-09", "features": "", "quality": "Alta", "UploadedBy": "conturera", "sub": ""}, {"lang": "Castellano", "info": "", "linksType": "direct_download", "added": "2013-10-18 10:57:32", "sprite": "bitshare", "idv": 3628832, "NickAddedBy": "Borju65", "price": "", "addedBy": 2400484, "url": "http://bitshare.com/?f=kd8kowrt", "host": "BitShare", "DateAdded": "2013-10-18", "features": "", "quality": "Alta", "UploadedBy": "Borju65", "sub": ""}], "title": "Capitulo 14", "season": 1, "mediaType": "1", "ids": 3799, "title_es": "Capitulo 14", "has_links": true, "haveLinks": true, "timestamp": 1417363177, "episode": 14, "idc": 542302}, {"num": 15, "name": "Capitulo 15", "links": [{"lang": "Castellano", "info": "", "linksType": "streaming", "added": "2013-11-05 03:17:54", "sprite": "videomegatv", "idv": 3789007, "NickAddedBy": "Borju65", "price": "", "addedBy": 2400484, "url": "http://videomega.tv/?ref=XdDbFEFUFP", "host": "VideoMega.tv", "DateAdded": "2013-11-05", "features": "", "quality": "Alta", "UploadedBy": "Borju65", "sub": ""}, {"lang": "Castellano", "info": "", "linksType": "direct_download", "added": "2014-11-30 16:59:38", "sprite": "freakshare", "idv": 11294481, "NickAddedBy": "parak314", "price": "", "addedBy": 3319309, "url": "http://freakshare.com/files/6bxy2ha6/Fmn.y.Cnsd.El.Orgll.dl.Trcr.Mnd.15.ByParak.avi.html", "host": "FreakShare", "DateAdded": "2014-11-30", "features": "", "quality": "Alta", "UploadedBy": "parak314", "sub": ""}, {"lang": "Castellano", "info": "", "linksType": "direct_download", "added": "2014-11-30 16:58:23", "sprite": "bitshare", "idv": 11294460, "NickAddedBy": "parak314", "price": "", "addedBy": 3319309, "url": "http://bitshare.com/?f=8gb2fl2v", "host": "BitShare", "DateAdded": "2014-11-30", "features": "", "quality": "Alta", "UploadedBy": "parak314", "sub": ""}, {"lang": "Castellano", "info": "", "linksType": "direct_download", "added": "2014-11-30 16:53:53", "sprite": "uploaded", "idv": 11294433, "NickAddedBy": "parak314", "price": "", "addedBy": 3319309, "url": "http://uploaded.to/file/pz1o9szd", "host": "uploaded", "DateAdded": "2014-11-30", "features": "", "quality": "Alta", "UploadedBy": "parak314", "sub": ""}, {"lang": "Castellano", "info": "", "linksType": "direct_download", "added": "2014-04-22 14:32:28", "sprite": "uploaded", "idv": 6164504, "NickAddedBy": "jorgereal", "price": "", "addedBy": 3581305, "url": "http://uploaded.to/file/h69m5ldf", "host": "uploaded", "DateAdded": "2014-04-22", "features": "", "quality": "Alta", "UploadedBy": "jorgereal", "sub": ""}, {"lang": "Castellano", "info": "", "linksType": "direct_download", "added": "2013-12-09 23:35:30", "sprite": "letitbit", "idv": 4213917, "NickAddedBy": "conturera", "price": "", "addedBy": 3136890, "url": "http://letitbit.net/download/43373.4fb053e3d0de953220b62339f883/Faemino_y_Cansado_-_El_Orgullo_del_Tercer_Mundo_Capitulo_1x15.avi.html", "host": "Letitbit", "DateAdded": "2013-12-09", "features": "", "quality": "Alta", "UploadedBy": "conturera", "sub": ""}, {"lang": "Castellano", "info": "", "linksType": "direct_download", "added": "2013-10-18 10:57:33", "sprite": "bitshare", "idv": 3628833, "NickAddedBy": "Borju65", "price": "", "addedBy": 2400484, "url": "http://bitshare.com/?f=gtucdtr4", "host": "BitShare", "DateAdded": "2013-10-18", "features": "", "quality": "Alta", "UploadedBy": "Borju65", "sub": ""}], "title": "Capitulo 15", "season": 1, "mediaType": "1", "ids": 3799, "title_es": "Capitulo 15", "has_links": true, "haveLinks": true, "timestamp": 1417363178, "episode": 15, "idc": 542304}, {"num": 16, "name": "Capitulo 16", "links": [{"lang": "Castellano", "info": "", "linksType": "streaming", "added": "2013-11-05 03:17:54", "sprite": "videomegatv", "idv": 3789008, "NickAddedBy": "Borju65", "price": "", "addedBy": 2400484, "url": "http://videomega.tv/?ref=VPBDaWXADc", "host": "VideoMega.tv", "DateAdded": "2013-11-05", "features": "", "quality": "Alta", "UploadedBy": "Borju65", "sub": ""}, {"lang": "Castellano", "info": "", "linksType": "direct_download", "added": "2014-11-30 16:59:40", "sprite": "freakshare", "idv": 11294482, "NickAddedBy": "parak314", "price": "", "addedBy": 3319309, "url": "http://freakshare.com/files/20hwkwnd/Fmn.y.Cnsd.El.Orgll.dl.Trcr.Mnd.16.ByParak.avi.html", "host": "FreakShare", "DateAdded": "2014-11-30", "features": "", "quality": "Alta", "UploadedBy": "parak314", "sub": ""}, {"lang": "Castellano", "info": "", "linksType": "direct_download", "added": "2014-11-30 16:58:26", "sprite": "bitshare", "idv": 11294461, "NickAddedBy": "parak314", "price": "", "addedBy": 3319309, "url": "http://bitshare.com/?f=uo0umicg", "host": "BitShare", "DateAdded": "2014-11-30", "features": "", "quality": "Alta", "UploadedBy": "parak314", "sub": ""}, {"lang": "Castellano", "info": "", "linksType": "direct_download", "added": "2014-11-30 16:54:08", "sprite": "uploaded", "idv": 11294434, "NickAddedBy": "parak314", "price": "", "addedBy": 3319309, "url": "http://uploaded.to/file/kd6c4xx4", "host": "uploaded", "DateAdded": "2014-11-30", "features": "", "quality": "Alta", "UploadedBy": "parak314", "sub": ""}, {"lang": "Castellano", "info": "", "linksType": "direct_download", "added": "2014-04-22 14:32:30", "sprite": "uploaded", "idv": 6164505, "NickAddedBy": "jorgereal", "price": "", "addedBy": 3581305, "url": "http://uploaded.to/file/7d4a2hhn", "host": "uploaded", "DateAdded": "2014-04-22", "features": "", "quality": "Alta", "UploadedBy": "jorgereal", "sub": ""}, {"lang": "Castellano", "info": "", "linksType": "direct_download", "added": "2013-12-09 23:35:32", "sprite": "letitbit", "idv": 4213919, "NickAddedBy": "conturera", "price": "", "addedBy": 3136890, "url": "http://letitbit.net/download/79297.7b467db89431894de48b879bd4f8/Faemino_y_Cansado_-_El_Orgullo_del_Tercer_Mundo_Capitulo_1x16.avi.html", "host": "Letitbit", "DateAdded": "2013-12-09", "features": "", "quality": "Alta", "UploadedBy": "conturera", "sub": ""}, {"lang": "Castellano", "info": "", "linksType": "direct_download", "added": "2013-10-18 10:57:34", "sprite": "bitshare", "idv": 3628834, "NickAddedBy": "Borju65", "price": "", "addedBy": 2400484, "url": "http://bitshare.com/?f=j1hk6bk9", "host": "BitShare", "DateAdded": "2013-10-18", "features": "", "quality": "Alta", "UploadedBy": "Borju65", "sub": ""}], "title": "Capitulo 16", "season": 1, "mediaType": "1", "ids": 3799, "title_es": "Capitulo 16", "has_links": true, "haveLinks": true, "timestamp": 1417363180, "episode": 16, "idc": 542306}]}, "imdb": "", "year": 1975, "plot": ["Faemino y Cansado es un d\u00fao espa\u00f1ol de humoristas que toma su nombre del apelativo art\u00edstico elegido por sus componentes, Carlos Faemino y Javier Cansado. Comenzaron su carrera en Madrid, Espa\u00f1a, con espect\u00e1culos callejeros, posteriormente en teatros y continuaron con apariciones en televisi\u00f3n, incluso con un programa propio, hasta la actualidad, en que siguen llenando teatros. Su humor, aunque suele etiquetarse como inclasificable, se puede considerar como absurdo, inteligente y surrealista."], "genres": ["Drama"], "compose": [{"role": " ", "name": "Jos\u00e9 Sol\u00e1"}], "title": "Faemino y Cansado", "plot_es": ["Faemino y Cansado es un d\u00fao espa\u00f1ol de humoristas que toma su nombre del apelativo art\u00edstico elegido por sus componentes, Carlos Faemino y Javier Cansado. Comenzaron su carrera en Madrid, Espa\u00f1a, con espect\u00e1culos callejeros, posteriormente en teatros y continuaron con apariciones en televisi\u00f3n, incluso con un programa propio, hasta la actualidad, en que siguen llenando teatros. Su humor, aunque suele etiquetarse como inclasificable, se puede considerar como absurdo, inteligente y surrealista."], "original_name": "Los casados y la menor", "mediaType": 1, "languages": ["Spanish"], "idm": 3799, "plot_en": ["Faemino y Cansado es un d\u00fao espa\u00f1ol de humoristas que toma su nombre del apelativo art\u00edstico elegido por sus componentes, Carlos Faemino y Javier Cansado. Comenzaron su carrera en Madrid, Espa\u00f1a, con espect\u00e1culos callejeros, posteriormente en teatros y continuaron con apariciones en televisi\u00f3n, incluso con un programa propio, hasta la actualidad, en que siguen llenando teatros. Su humor, aunque suele etiquetarse como inclasificable, se puede considerar como absurdo, inteligente y surrealista."], "status": 3, "timestamp": 1419116400, "lists": [{"_idMediaList": {"$id": "530292240a358a811d8b4567"}, "date": {"usec": 600000, "sec": 1393379517}, "title": "lo que me gusta"}, {"_idMediaList": {"$id": "536e7a9083f2f010788b456d"}, "date": {"usec": 630000, "sec": 1399750130}, "title": "Para ver"}, {"_idMediaList": {"$id": "537a700a0822cc771d8b456a"}, "date": {"usec": 730000, "sec": 1400537893}, "title": "Cine por ver"}, {"_idMediaList": {"$id": "53876a750822ccc4498b4569"}, "date": {"usec": 461000, "sec": 1401383868}, "title": "FINIQUITADAS"}, {"_idMediaList": {"$id": "53cbe6e887186d286a8b4568"}, "date": {"usec": 788000, "sec": 1405872300}, "title": "SeriesInfancia"}, {"_idMediaList": {"$id": "53db08560822ccf7198b4568"}, "date": {"usec": 821000, "sec": 1406864389}, "title": "series"}], "broadcast": "online", "produce": [], "total_users": 427, "seasons": 1, "aka": null, "director": [{"role": null, "name": "Joaqu\u00edn Coll Espona"}], "rate_summary": {"aggregate": {"1": 0, "3": 3, "2": 3, "5": 61, "4": 22}}, "country": ["Spain"], "cast": [{"role": "", "name": "Rafael Anglada"}, {"role": "", "name": "Enric Casamitjana"}, {"role": " ", "name": "Francisco J. Escriva"}, {"role": "", "name": "Javier Escriv\u00e1"}, {"role": "", "name": "Alberto Fern\u00e1ndez de Rosa"}, {"role": "", "name": "Emilio Laguna"}, {"role": "", "name": "Daniel Mart\u00edn"}, {"role": "", "name": "Venancio Muro"}, {"role": "", "name": "Jos\u00e9 Riesgo"}, {"role": "", "name": "Fernando Sancho"}], "write": [{"role": null, "name": "Joaqu\u00edn Coll Espona"}], "episodeUserCreator": {"1": {"11": "Mini.ma7", "10": "Mini.ma7", "13": "Mini.ma7", "12": "Mini.ma7", "15": "Borju65", "14": "Borju65", "16": "Borju65", "1": "ertigre", "3": "pedrogadura", "2": "ertigre", "5": "Mini.ma7", "4": "Mini.ma7", "7": "Mini.ma7", "6": "Mini.ma7", "9": "Mini.ma7", "8": "Mini.ma7"}}, "id_media": "59EN9K47CT", "runtime": "101", "lists_num": 8}