{"rating": 5, "links": [], "maingenre": "Short", "imdb": "tt0321100", "year": "1974", "plot": [""], "genres": ["Short"], "compose": [], "title": "An Afghan Village", "plot_es": [""], "original_name": "An Afghan Village", "mediaType": 2, "write": [], "plot_en": [""], "status": 3, "timestamp": 1419634800, "broadcast": "online", "produce": [], "total_users": 0, "id_media": "Z64FAF57KKWVN4A", "director": [{"name": "Norman Miller"}], "languages": [], "country": ["Afghanistan"], "cast": [], "idm": 1267488, "episodeUserCreator": [], "aka": null}