{"rating": 5, "links": [], "maingenre": "Documentary", "imdb": "tt1127725", "year": "1981", "plot": ["Experimental alternative technology for village India."], "genres": ["Documentary"], "compose": [], "title": "West of Bangalore", "plot_es": ["Experimental alternative technology for village India."], "original_name": "West of Bangalore", "mediaType": 3, "languages": ["English"], "idm": 1196295, "plot_en": ["Experimental alternative technology for village India."], "status": 3, "timestamp": 1419116400, "broadcast": "online", "produce": [{"imdb": "0043107", "name": "British Broadcasting Corporation (BBC)"}], "total_users": 0, "id_media": "RED9W4ZDNE3E374", "director": [{"name": "Christopher Sykes"}], "country": ["UK"], "cast": [], "write": [], "episodeUserCreator": [], "aka": null, "runtime": "50"}